vermouth/__init__.py
vermouth/citation_parser.py
vermouth/edge_tuning.py
vermouth/ffinput.py
vermouth/file_writer.py
vermouth/forcefield.py
vermouth/geometry.py
vermouth/graph_utils.py
vermouth/ismags.py
vermouth/log_helpers.py
vermouth/map_input.py
vermouth/map_parser.py
vermouth/molecule.py
vermouth/parser_utils.py
vermouth/selectors.py
vermouth/system.py
vermouth/truncating_formatter.py
vermouth/utils.py
vermouth/data/__init__.py
vermouth/data/citations.bib
vermouth/data/data.py
vermouth/data/quotes.txt
vermouth/data/force_fields/amber/aminoacids.rtp
vermouth/data/force_fields/amber/links.ff
vermouth/data/force_fields/amber/modifications.ff
vermouth/data/force_fields/charmm/aminoacids.rtp
vermouth/data/force_fields/charmm/links.ff
vermouth/data/force_fields/charmm/lipidations.rtp
vermouth/data/force_fields/charmm/modifications.ff
vermouth/data/force_fields/charmm/small_molecule_charmm.ff
vermouth/data/force_fields/elnedyn21/aminoacids.ff
vermouth/data/force_fields/elnedyn21/citations.bib
vermouth/data/force_fields/elnedyn21/general.ff
vermouth/data/force_fields/elnedyn21/modifications.ff
vermouth/data/force_fields/elnedyn22/aminoacids.ff
vermouth/data/force_fields/elnedyn22/citations.bib
vermouth/data/force_fields/elnedyn22/general.ff
vermouth/data/force_fields/elnedyn22/modifications.ff
vermouth/data/force_fields/elnedyn22p/aminoacids.ff
vermouth/data/force_fields/elnedyn22p/citations.bib
vermouth/data/force_fields/elnedyn22p/general.ff
vermouth/data/force_fields/elnedyn22p/modifications.ff
vermouth/data/force_fields/gromos/aminoacids.rtp
vermouth/data/force_fields/gromos/cofactors.ff
vermouth/data/force_fields/gromos/modifications.ff
vermouth/data/force_fields/martini22/aminoacids.ff
vermouth/data/force_fields/martini22/citations.bib
vermouth/data/force_fields/martini22/general.ff
vermouth/data/force_fields/martini22/modifications.ff
vermouth/data/force_fields/martini22/nucleotides.ff
vermouth/data/force_fields/martini22p/aminoacids.ff
vermouth-0.15.0.dist-info/licenses/LICENSE
vermouth-0.15.0.dist-info/METADATA
vermouth-0.15.0.dist-info/WHEEL
vermouth-0.15.0.dist-info/pbr.json
vermouth-0.15.0.dist-info/top_level.txt
vermouth-0.15.0.dist-info/RECORD
