Metadata-Version: 2.4
Name: vermouth
Version: 0.15.0
Home-page: https://github.com/marrink-lab/vermouth-martinize
Author: P C Kroon
Author-email: p.c.kroon@rug.nl
License: Apache 2.0
Keywords: martini MD martinize
Classifier: Development Status :: 5 - Production/Stable
Classifier: Environment :: Console
Classifier: Intended Audience :: Developers
Classifier: Intended Audience :: Science/Research
Classifier: License :: OSI Approved :: Apache Software License
Classifier: Operating System :: OS Independent
Classifier: Programming Language :: Python :: 3
Classifier: Programming Language :: Python :: 3.9
Classifier: Programming Language :: Python :: 3.10
Classifier: Programming Language :: Python :: 3.11
Classifier: Programming Language :: Python :: 3.12
Classifier: Topic :: Scientific/Engineering :: Bio-Informatics
Classifier: Topic :: Scientific/Engineering :: Chemistry
License-File: LICENSE
Requires-Dist: pbr
Requires-Dist: numpy
Requires-Dist: networkx>=2.0
Requires-Dist: scipy
Provides-Extra: mdtraj
Requires-Dist: mdtraj; extra == "mdtraj"
Provides-Extra: pycifrw
Requires-Dist: PyCifRW; extra == "pycifrw"
Dynamic: author
Dynamic: author-email
Dynamic: classifier
Dynamic: description
Dynamic: description-content-type
Dynamic: keywords
Dynamic: license
Dynamic: license-file
